loguru_discord/__init__.py
loguru_discord/py.typed
loguru_discord/sink.py
loguru_discord/sink.pyi
loguru_discord-1.4.0.dist-info/METADATA
loguru_discord-1.4.0.dist-info/WHEEL
loguru_discord-1.4.0.dist-info/licenses/LICENSE
loguru_discord-1.4.0.dist-info/RECORD
