Metadata-Version: 2.3
Name: loguru-discord
Version: 1.4.0
Summary: Lightweight sink for Loguru that sends logs to Discord via webhook.
Project-URL: Repository, https://github.com/EthanC/Loguru-Discord
Project-URL: Issues, https://github.com/EthanC/Loguru-Discord/issues
Project-URL: Changelog, https://github.com/EthanC/Loguru-Discord/commits/main/
Project-URL: Twitter, https://twitter.com/Mxtive
License-Expression: MIT
License-File: LICENSE
Keywords: discord,logging,loguru,sink,webhook
Classifier: Development Status :: 5 - Production/Stable
Classifier: Intended Audience :: Developers
Classifier: License :: OSI Approved :: MIT License
Classifier: Natural Language :: English
Classifier: Operating System :: OS Independent
Classifier: Programming Language :: Python :: 3.12
Classifier: Topic :: Internet
Classifier: Topic :: Software Development :: Libraries
Classifier: Topic :: Software Development :: Libraries :: Python Modules
Classifier: Typing :: Typed
Requires-Python: >=3.12
Requires-Dist: discord-webhook>=1.3.1
